{
  "project_info": {
    "project_number": "453370936021",
    "project_id": "ironcore-gear",
    "storage_bucket": "ironcore-gear.firebasestorage.app"
  },
  "client": [
    {
      "client_info": {
        "mobilesdk_app_id": "1:453370936021:android:dfc85639d55967c1ae405c",
        "android_client_info": {
          "package_name": "ironcore.com"
        }
      },
      "oauth_client": [],
      "api_key": [
        {
          "current_key": "AIzaSyAXgQq_tsHWrRYgaSx-QWKlM8-UMrGWSuE"
        }
      ],
      "services": {
        "appinvite_service": {
          "other_platform_oauth_client": []
        }
      }
    }
  ],
  "configuration_version": "1"
}